polars_ta/__init__.py
polars_ta/_version.py
polars_ta/noise.py
polars_ta/candles/__init__.py
polars_ta/candles/cdl1.py
polars_ta/candles/cdl1_limit.py
polars_ta/candles/cdl2.py
polars_ta/labels/__init__.py
polars_ta/labels/_nb.py
polars_ta/labels/future.py
polars_ta/performance/__init__.py
polars_ta/performance/drawdown.py
polars_ta/performance/returns.py
polars_ta/prefix/__init__.py
polars_ta/prefix/cdl.py
polars_ta/prefix/labels.py
polars_ta/prefix/reports.py
polars_ta/prefix/ta.py
polars_ta/prefix/talib.py
polars_ta/prefix/tdx.py
polars_ta/prefix/vec.py
polars_ta/prefix/wq.py
polars_ta/reports/__init__.py
polars_ta/reports/cicc.py
polars_ta/ta/README.md
polars_ta/ta/__init__.py
polars_ta/ta/momentum.py
polars_ta/ta/operators.py
polars_ta/ta/overlap.py
polars_ta/ta/price.py
polars_ta/ta/statistic.py
polars_ta/ta/transform.py
polars_ta/ta/volatility.py
polars_ta/ta/volume.py
polars_ta/talib/README.md
polars_ta/talib/__init__.py
polars_ta/tdx/README.md
polars_ta/tdx/__init__.py
polars_ta/tdx/_chip.py
polars_ta/tdx/_nb.py
polars_ta/tdx/_slow.py
polars_ta/tdx/arithmetic.py
polars_ta/tdx/choice.py
polars_ta/tdx/energy.py
polars_ta/tdx/logical.py
polars_ta/tdx/moving_average.py
polars_ta/tdx/over_bought_over_sold.py
polars_ta/tdx/pattern.py
polars_ta/tdx/pattern_feature.py
polars_ta/tdx/pressure_support.py
polars_ta/tdx/reference.py
polars_ta/tdx/statistic.py
polars_ta/tdx/times.py
polars_ta/tdx/trend.py
polars_ta/tdx/trend_feature.py
polars_ta/tdx/volume.py
polars_ta/utils/__init__.py
polars_ta/utils/numba_.py
polars_ta/utils/pit.py
polars_ta/utils/withs.py
polars_ta/wq/__init__.py
polars_ta/wq/_nb.py
polars_ta/wq/_slow.py
polars_ta/wq/arithmetic.py
polars_ta/wq/cross_sectional.py
polars_ta/wq/half_life.py
polars_ta/wq/logical.py
polars_ta/wq/preprocess.py
polars_ta/wq/time_series.py
polars_ta/wq/transformational.py
polars_ta/wq/vector.py
polars_ta-0.5.16.dist-info/METADATA
polars_ta-0.5.16.dist-info/WHEEL
polars_ta-0.5.16.dist-info/licenses/LICENSE
polars_ta-0.5.16.dist-info/RECORD
