Metadata-Version: 2.4
Name: polars_ta
Version: 0.5.16
Summary: polars expressions
Author-email: wukan <wu-kan@163.com>
License: MIT License
License-File: LICENSE
Keywords: expression,polars,talib
Classifier: Development Status :: 4 - Beta
Classifier: Programming Language :: Python
Requires-Python: >=3.8
Requires-Dist: more-itertools
Requires-Dist: numba
Requires-Dist: numpy
Requires-Dist: pandas
Requires-Dist: polars-ols>=0.3.0
Requires-Dist: polars>=1.28.0
Provides-Extra: talib
Requires-Dist: ta-lib; extra == 'talib'
